{
    "seed": 154367,
    "experiment_name": "gan_data20k_lr1e-6",
    "batch_size": 256,
    "num_epochs": 200,
    "input_max_len": 20000,
    "learning_rate": 1e-6,
    "weight_decay_coefficient": 1e-6,
    "discriminator": {
        "kernel_sizes": [4, 4, 4, 4, 4, 4],
        "strides": [2, 2, 2, 2, 2, 2],
        "num_residual_channels": [16, 32, 64, 128, 128, 128]
    },
    "generator": {
        "latent_dim": 64,
        "latent_length": 310,
        "kernel_sizes": [8, 4, 4, 4, 4, 4, 1024],
        "strides": [2, 2, 2, 2, 2, 2, 1],
        "comment_strides": "TODO: Check receptive field, maybe use dilations?",
        "dilations": [1, 2, 4, 16, 2, 4, 1],
        "comment_dilations": "effective kernel size = kernel + (kernel - 1)*(dilation -1)",
        "paddings": [12, 12, 10, 10, 8, 4, 0],
        "out_paddings": [0, 0, 0, 0, 0, 0, 0], 
        "comment_out_paddings": "output = (input - 1)*stride - 2*padding + kernel + output_padding",
        "num_residual_channels": [128, 128, 128, 64, 32, 16, 1],
        "speaker_dim": 64
    }
}